npyx/CONFIG.py
npyx/__init__.py
npyx/behav.py
npyx/circuitProphyler.py
npyx/corr.py
npyx/datasets.py
npyx/feat.py
npyx/gl.py
npyx/h5.py
npyx/histo.py
npyx/info.py
npyx/inout.py
npyx/merger.py
npyx/metrics.py
npyx/ml.py
npyx/model.py
npyx/plot.py
npyx/plot_utils.py
npyx/preprocess.py
npyx/spk_t.py
npyx/spk_wvf.py
npyx/stats.py
npyx/testing.py
npyx/utils.py
npyx/c4/__init__.py
npyx/c4/acg_augmentations.py
npyx/c4/acg_vs_firing_rate.py
npyx/c4/dataset_init.py
npyx/c4/dl_transforms.py
npyx/c4/dl_utils.py
npyx/c4/encode_features.py
npyx/c4/misc.py
npyx/c4/monkey_dataset_init.py
npyx/c4/plots_functions.py
npyx/c4/predict_cell_types.py
npyx/c4/run_baseline_classifier.py
npyx/c4/run_deep_classifier.py
npyx/c4/waveform_augmentations.py
npyx-4.1.1.dist-info/LICENSE.md
npyx-4.1.1.dist-info/METADATA
npyx-4.1.1.dist-info/WHEEL
npyx-4.1.1.dist-info/dependency_links.txt
npyx-4.1.1.dist-info/entry_points.txt
npyx-4.1.1.dist-info/top_level.txt
npyx-4.1.1.dist-info/RECORD
