Metadata-Version: 2.1
Name: npyx
Version: 4.1.1
Summary: Python routines dealing with Neuropixels data.
Home-page: https://github.com/Npix-routines/NeuroPyxels
Author: Maxime Beau
Author-email: maximebeaujeanroch047@gmail.com
Keywords: neuropixels,kilosort,phy,data analysis,electrophysiology,neuroscience
Classifier: Programming Language :: Python
Classifier: License :: OSI Approved :: GNU General Public License v3 (GPLv3)
Requires-Python: <3.12
License-File: LICENSE.md
Requires-Dist: ipython
Requires-Dist: numpy
Requires-Dist: scipy ==1.10.0
Requires-Dist: pandas
Requires-Dist: numba
Requires-Dist: statsmodels
Requires-Dist: matplotlib
Requires-Dist: cmcrameri
Requires-Dist: scikit-learn
Requires-Dist: imbalanced-learn
Requires-Dist: networkx
Requires-Dist: psutil
Requires-Dist: joblib >=1.3
Requires-Dist: tqdm
Requires-Dist: h5py
Requires-Dist: seaborn
Requires-Dist: cachecache
Provides-Extra: c4
Requires-Dist: torch ==1.13.1 ; extra == 'c4'
Requires-Dist: torchvision ==0.14.1 ; extra == 'c4'
Requires-Dist: torchaudio ==0.13.1 ; extra == 'c4'
Requires-Dist: laplace-torch ; extra == 'c4'
Requires-Dist: requests ; extra == 'c4'
Requires-Dist: dill ; extra == 'c4'
Requires-Dist: tabulate ; extra == 'c4'
